qaviton_processes/__init__.py
qaviton_processes/multi_processing.py
qaviton_processes/system.py
qaviton_processes-2019.11.1.13.50.43.917059.dist-info/LICENSE
qaviton_processes-2019.11.1.13.50.43.917059.dist-info/METADATA
qaviton_processes-2019.11.1.13.50.43.917059.dist-info/WHEEL
qaviton_processes-2019.11.1.13.50.43.917059.dist-info/top_level.txt
qaviton_processes-2019.11.1.13.50.43.917059.dist-info/RECORD
