Metadata-Version: 2.1
Name: qaviton-processes
Version: 2019.11.1.13.50.43.917059
Summary: qaviton help functions to make things simple
Home-page: https://github.com/qaviton/qaviton_processes
Author: qaviton
Author-email: info@qaviton.com
License: apache-2.0
Platform: UNKNOWN
Classifier: Programming Language :: Python :: 3.7
Requires-Dist: pyescape
